svgpathtools/__init__.py
svgpathtools/bezier.py
svgpathtools/document.py
svgpathtools/misctools.py
svgpathtools/parser.py
svgpathtools/path.py
svgpathtools/paths2svg.py
svgpathtools/polytools.py
svgpathtools/smoothing.py
svgpathtools/svg_io_sax.py
svgpathtools/svg_to_paths.py
svgpathtools-1.6.1.dist-info/LICENSE.txt
svgpathtools-1.6.1.dist-info/METADATA
svgpathtools-1.6.1.dist-info/WHEEL
svgpathtools-1.6.1.dist-info/top_level.txt
svgpathtools-1.6.1.dist-info/RECORD
