Metadata-Version: 2.1
Name: svgpathtools
Version: 1.6.1
Summary: A collection of tools for manipulating and analyzing SVG Path objects and Bezier curves.
Home-page: https://github.com/mathandy/svgpathtools
Download-URL: https://github.com/mathandy/svgpathtools/releases/download/1.6.1/svgpathtools-1.6.1-py2.py3-none-any.whl
Author: Andy Port
Author-email: AndyAPort@gmail.com
License: MIT
Keywords: svg,svg path,svg.path,bezier,parse svg path,display svg
Platform: OS Independent
Classifier: Development Status :: 4 - Beta
Classifier: Intended Audience :: Developers
Classifier: License :: OSI Approved :: MIT License
Classifier: Operating System :: OS Independent
Classifier: Programming Language :: Python :: 2
Classifier: Programming Language :: Python :: 3
Classifier: Programming Language :: Python :: 2.7
Classifier: Programming Language :: Python :: 3.5
Classifier: Programming Language :: Python :: 3.6
Classifier: Programming Language :: Python :: 3.7
Classifier: Programming Language :: Python :: 3.8
Classifier: Programming Language :: Python :: 3.9
Classifier: Programming Language :: Python :: 3.10
Classifier: Programming Language :: Python :: 3.11
Classifier: Topic :: Multimedia :: Graphics :: Editors :: Vector-Based
Classifier: Topic :: Scientific/Engineering
Classifier: Topic :: Scientific/Engineering :: Image Recognition
Classifier: Topic :: Scientific/Engineering :: Information Analysis
Classifier: Topic :: Scientific/Engineering :: Mathematics
Classifier: Topic :: Scientific/Engineering :: Visualization
Classifier: Topic :: Software Development :: Libraries :: Python Modules
License-File: LICENSE.txt
